tljh_repo2docker/__init__.py
tljh_repo2docker/__main__.py
tljh_repo2docker/_version.py
tljh_repo2docker/app.py
tljh_repo2docker/base.py
tljh_repo2docker/binderhub_builder.py
tljh_repo2docker/binderhub_log.py
tljh_repo2docker/builder.py
tljh_repo2docker/dbutil.py
tljh_repo2docker/docker.py
tljh_repo2docker/environments.py
tljh_repo2docker/logs.py
tljh_repo2docker/model.py
tljh_repo2docker/servers.py
tljh_repo2docker/servers_api.py
tljh_repo2docker/alembic/alembic.ini
tljh_repo2docker/alembic/env.py
tljh_repo2docker/alembic/script.py.mako
tljh_repo2docker/alembic/versions/ac1b4e7e52f3_first_migration.py
tljh_repo2docker/database/manager.py
tljh_repo2docker/database/model.py
tljh_repo2docker/database/schemas.py
tljh_repo2docker/static/images/jupyterhub-80.png
tljh_repo2docker/static/js/0f86a30ca7e981fcfc99.woff2
tljh_repo2docker/static/js/1123fece34276ab96f52.woff2
tljh_repo2docker/static/js/148734d63bd96c6e964f.woff2
tljh_repo2docker/static/js/18e6d3d94a7a3bb963b1.woff2
tljh_repo2docker/static/js/1acaa4ce1293ac2c4280.woff2
tljh_repo2docker/static/js/1fb2c6d685bfb888cfa3.woff2
tljh_repo2docker/static/js/2422af9ea58377139eb0.woff
tljh_repo2docker/static/js/2466fcd6ea368f16f5b7.woff
tljh_repo2docker/static/js/251bfb34b63828349c7c.woff2
tljh_repo2docker/static/js/28728bc8c64fa1bfd905.woff
tljh_repo2docker/static/js/2d5875b032a1cca91eb2.woff2
tljh_repo2docker/static/js/2dac09a8617653d1edf4.woff
tljh_repo2docker/static/js/31476620b88eec076438.woff2
tljh_repo2docker/static/js/374501ec719fcb3565cb.woff2
tljh_repo2docker/static/js/3d32572dd5951c418e5b.woff2
tljh_repo2docker/static/js/3ef0cbd46ba817c7a976.woff
tljh_repo2docker/static/js/41db483cb764343fca71.woff2
tljh_repo2docker/static/js/432ae4faf4868f2e3229.woff
tljh_repo2docker/static/js/481c6bfe225ffaff4d13.woff
tljh_repo2docker/static/js/534893d6b1240067604a.woff
tljh_repo2docker/static/js/599f66a60bdf974e578e.woff2
tljh_repo2docker/static/js/5c8100481d4e784afbf2.woff2
tljh_repo2docker-3.0.5.dist-info/METADATA
tljh_repo2docker-3.0.5.dist-info/WHEEL
tljh_repo2docker-3.0.5.dist-info/entry_points.txt
tljh_repo2docker-3.0.5.dist-info/licenses/LICENSE
tljh_repo2docker-3.0.5.dist-info/RECORD
