Metadata-Version: 2.4
Name: tljh-repo2docker
Version: 3.0.5
License: BSD 3-Clause License
License-File: LICENSE
Classifier: Programming Language :: Python :: 3 :: Only
Classifier: Programming Language :: Python :: 3.10
Classifier: Programming Language :: Python :: 3.11
Classifier: Programming Language :: Python :: 3.12
Classifier: Programming Language :: Python :: 3.13
Requires-Python: >=3.10
Requires-Dist: aiodocker<0.22.0,>=0.21.0
Requires-Dist: aiosqlite~=0.19.0
Requires-Dist: alembic<1.15,>=1.14
Requires-Dist: dockerspawner<15.0.0,>=14.0.0
Requires-Dist: httpx
Requires-Dist: jupyter-client<8,>=6.1
Requires-Dist: jupyter-repo2docker<2025,>=2024
Requires-Dist: pydantic<3,>=2
Requires-Dist: sqlalchemy<3,>=2
